{"questions":[{"title":"你喜欢游泳吗？","answer":"Do you enjoy swimming?"},{"title":"你喜欢吃我做的鸡翅吗？","answer":"Do you enjoy eating the chicken wings I cook?"},{"title":"你和你的家人喜欢我设计的旅程吗？","answer":"Do you and your families enjoy the journey I have designed?"},{"title":"你的儿子有好的逻辑思维，他喜欢数学吗？","answer":"Your son has a good logical thinking, does he enjoy maths?"},{"title":"你喜欢在夕阳西下的时候独自一人走在海边吗？","answer":"Do you enjoy walking at the seaside alone when the sun is setting?"}],"dialogs":[{"title":["——你喜欢看言情小说吗？它可以让我快乐。","——看言情小说就是浪费时间。"],"answer":[{"en":"Do you enjoy reading romantic novels?It can make me happy."},{"en":"Reading romantic novels is a waste of time."}]},{"title":["——你喜欢踏青吗？","——喜欢，阳光明媚、空气清新。"],"answer":[{"en":"Do you enjoy going for a walk in the country in spring?"},{"en":"Yes, the sun is shining and the air is fresh."}]}]}